{
	"configurations" : 
	[
		{
			"directories" : 
			[
				{
					"build" : ".",
					"jsonFile" : "directory-.-Debug-d0094a50bb2071803777.json",
					"minimumCMakeVersion" : 
					{
						"string" : "3.28"
					},
					"projectIndex" : 0,
					"source" : ".",
					"targetIndexes" : 
					[
						0,
						1,
						2
					]
				}
			],
			"name" : "Debug",
			"projects" : 
			[
				{
					"directoryIndexes" : 
					[
						0
					],
					"name" : "S4ED",
					"targetIndexes" : 
					[
						0,
						1,
						2
					]
				}
			],
			"targets" : 
			[
				{
					"directoryIndex" : 0,
					"id" : "S4ED10::@6890427a1f51a3e7e1df",
					"jsonFile" : "target-S4ED10-Debug-d5d0a86cfd07b2ebdfe8.json",
					"name" : "S4ED10",
					"projectIndex" : 0
				},
				{
					"directoryIndex" : 0,
					"id" : "S4ED9::@6890427a1f51a3e7e1df",
					"jsonFile" : "target-S4ED9-Debug-3f4c6b4a46e6fb9ebb64.json",
					"name" : "S4ED9",
					"projectIndex" : 0
				},
				{
					"directoryIndex" : 0,
					"id" : "S4ED9N::@6890427a1f51a3e7e1df",
					"jsonFile" : "target-S4ED9N-Debug-9bfbc639b04305c73ba9.json",
					"name" : "S4ED9N",
					"projectIndex" : 0
				}
			]
		}
	],
	"kind" : "codemodel",
	"paths" : 
	{
		"build" : "C:/Users/Diego Ochoa/CLionProjects/S4ED/cmake-build-debug",
		"source" : "C:/Users/Diego Ochoa/CLionProjects/S4ED"
	},
	"version" : 
	{
		"major" : 2,
		"minor" : 6
	}
}
